impipes/__init__.py
impipes/filters.py
impipes/pipes.py
impipes-0.1.8.dist-info/WHEEL
impipes-0.1.8.dist-info/METADATA
impipes-0.1.8.dist-info/RECORD
