Metadata-Version: 2.1
Name: impipes
Version: 0.1.8
Summary: 
Home-page: https://impipes.rtfd.io
License: MIT
Keywords: Image enhancement,Image pipelines,Image processing
Author: Rodolfo Ferro
Author-email: rodolfoferroperez@gmail.com
Requires-Python: >=3.6,<4.0
Classifier: License :: OSI Approved :: MIT License
Classifier: Operating System :: OS Independent
Classifier: Programming Language :: Python :: 3
Classifier: Programming Language :: Python :: 3.6
Classifier: Programming Language :: Python :: 3.7
Requires-Dist: matplotlib (>=3.1,<4.0)
Requires-Dist: numpy (>=1.17,<2.0)
Requires-Dist: opencv-python (>=4.1,<5.0)
Requires-Dist: scipy (>=1.3,<2.0)
Requires-Dist: wget (>=3.2,<4.0)
Project-URL: Repository, https://github.com/RodolfoFerro/impipes
